{
  "id": "cmni9uglx002sv17ip1pgv36e",
  "apn": "78-9-688-72",
  "address": "8145 Dry Creek Rd",
  "county": "Oconee",
  "state": "SC",
  "acreage": 640,
  "lat": 34.7043,
  "lon": -82.9271,
  "zoning": "conservation",
  "description": "640-acre conservation tract in Oconee County, SC. 39% pasture, 12% forest, 13% wetland, 36% developed. 43 miles from Greenville. Gravel road access. Elevation 1671 ft.",
  "createdAt": "2026-04-03T02:15:32.758Z",
  "updatedAt": "2026-04-03T02:15:32.758Z",
  "listings": [
    {
      "id": "cmni9ugn50091v17irxqdcri7",
      "parcelId": "cmni9uglx002sv17ip1pgv36e",
      "sourceId": "cmni9ugjf0006v17ijqnwe4qb",
      "externalId": "landwatch-775587",
      "url": "https://www.landwatch.com/listing/landwatch-775587",
      "title": "Scenic 640-Acre Conservation Tract in Oconee County",
      "price": 4697600,
      "pricePerAcre": 7340,
      "status": "listed",
      "photos": "[\"https://images.landscout.dev/landwatch-775587/aerial-1.jpg\",\"https://images.landscout.dev/landwatch-775587/ground-1.jpg\"]",
      "metadata": "{\"originalListDate\":\"2025-07-04\",\"daysOnMarket\":287,\"broker\":null}",
      "firstSeen": "2026-04-03T02:15:32.802Z",
      "lastSeen": "2026-04-03T02:15:32.802Z",
      "createdAt": "2026-04-03T02:15:32.802Z",
      "updatedAt": "2026-04-03T02:15:32.802Z",
      "sourceName": "LandWatch"
    },
    {
      "id": "cmni9ugn60093v17ipr0sx5tg",
      "parcelId": "cmni9uglx002sv17ip1pgv36e",
      "sourceId": "cmni9ugjf0002v17i3v49xs5g",
      "externalId": "lands-of-america-547536",
      "url": "https://www.landsofamerica.com/listing/lands-of-america-547536",
      "title": "Pristine 640-Acre Wilderness Tract in Oconee County",
      "price": 4791552,
      "pricePerAcre": 7487,
      "status": "listed",
      "photos": "[\"https://images.landscout.dev/lands-of-america-547536/aerial-1.jpg\",\"https://images.landscout.dev/lands-of-america-547536/ground-1.jpg\"]",
      "metadata": "{\"originalListDate\":\"2025-09-02\",\"daysOnMarket\":241,\"broker\":null}",
      "firstSeen": "2026-04-03T02:15:32.802Z",
      "lastSeen": "2026-04-03T02:15:32.802Z",
      "createdAt": "2026-04-03T02:15:32.802Z",
      "updatedAt": "2026-04-03T02:15:32.802Z",
      "sourceName": "Lands of America"
    },
    {
      "id": "cmni9ugn60095v17idszgg99h",
      "parcelId": "cmni9uglx002sv17ip1pgv36e",
      "sourceId": "cmni9ugjf000bv17ismj5rg2h",
      "externalId": "nai-land-839809",
      "url": "https://www.nailand.com/listing/nai-land-839809",
      "title": "Turnkey 640-Acre Conservation Tract in Oconee County",
      "price": 4650624,
      "pricePerAcre": 7267,
      "status": "listed",
      "photos": "[\"https://images.landscout.dev/nai-land-839809/aerial-1.jpg\",\"https://images.landscout.dev/nai-land-839809/ground-1.jpg\"]",
      "metadata": "{\"originalListDate\":\"2025-09-19\",\"daysOnMarket\":298,\"broker\":\"NAI Land\"}",
      "firstSeen": "2026-04-03T02:15:32.803Z",
      "lastSeen": "2026-04-03T02:15:32.803Z",
      "createdAt": "2026-04-03T02:15:32.803Z",
      "updatedAt": "2026-04-03T02:15:32.803Z",
      "sourceName": "NAI Land"
    }
  ],
  "features": {
    "id": "cmni9uglx002tv17icxc3stnp",
    "parcelId": "cmni9uglx002sv17ip1pgv36e",
    "landCoverMix": "{\"forest\":100}",
    "waterPresence": false,
    "waterFeatures": "[]",
    "metroDistance": 31.9,
    "nearestMetro": "Greenville, SC",
    "slopeStats": "{\"avgSlope\":2.3,\"maxSlope\":null,\"pctOver15\":0}",
    "soilsQuality": 9,
    "roadAccess": "gravel",
    "easements": null,
    "powerDistance": 4.7,
    "waterDistance": null,
    "sewerDistance": 17.7,
    "fiberDistance": 22.4,
    "gasDistance": 22.7,
    "inFloodway": false,
    "floodZone": "X",
    "wetlandsPercent": 29.4,
    "elevation": 893,
    "createdAt": "2026-04-03T02:15:32.758Z",
    "updatedAt": "2026-04-03T02:16:54.221Z"
  },
  "fitScore": {
    "id": "cmni9uglx002uv17i1hguzdit",
    "parcelId": "cmni9uglx002sv17ip1pgv36e",
    "overallScore": 64,
    "scoreBreakdown": "{\"acreage\":100,\"landCoverMix\":20,\"waterPresence\":30,\"metroProximity\":55,\"slope\":100,\"soils\":90,\"roadAccess\":75,\"easementPenalty\":100,\"utilities\":8}",
    "topReasons": "[\"+ Ideal acreage for target range (100)\",\"+ Favorable terrain (100)\",\"+ High-quality soils (90)\",\"- No water features detected (30)\",\"- Utilities distant or unavailable (8)\"]",
    "autoFailed": false,
    "autoFailReason": null,
    "calculatedAt": "2026-04-03T02:16:54.225Z"
  },
  "deal": null,
  "ownership": null
}