{
  "id": "cmni9yocp005vv1nao88h8ygw",
  "apn": "75-6-226-15",
  "address": "6766 County Rd 112",
  "county": "Blount",
  "state": "AL",
  "acreage": 264,
  "lat": 33.99659999999999,
  "lon": -86.7067,
  "zoning": "rural-residential",
  "description": "264-acre rural-residential tract in Blount County, AL. 55% forest, 45% wetland. Water features include pond. 48 miles from Birmingham. Paved road access. Elevation 1744 ft.",
  "createdAt": "2026-04-03T02:18:49.417Z",
  "updatedAt": "2026-04-03T02:18:49.417Z",
  "listings": [
    {
      "id": "cmni9yodt00bxv1nasdv1ebrx",
      "parcelId": "cmni9yocp005vv1nao88h8ygw",
      "sourceId": "cmni9yo7z0000v1naemtfmt98",
      "externalId": "landwatch-219384",
      "url": "https://www.landwatch.com/listing/landwatch-219384",
      "title": "Scenic 264-Acre Estate Tract in Blount County",
      "price": 1635216,
      "pricePerAcre": 6194,
      "status": "off-market",
      "photos": "[\"https://images.landscout.dev/landwatch-219384/aerial-1.jpg\",\"https://images.landscout.dev/landwatch-219384/ground-1.jpg\"]",
      "metadata": "{\"originalListDate\":\"2025-11-08\",\"daysOnMarket\":20,\"broker\":null}",
      "firstSeen": "2026-04-03T02:18:49.458Z",
      "lastSeen": "2026-04-03T02:18:49.458Z",
      "createdAt": "2026-04-03T02:18:49.458Z",
      "updatedAt": "2026-04-03T02:18:49.458Z",
      "sourceName": "LandWatch"
    },
    {
      "id": "cmni9yodu00bzv1nameudkprw",
      "parcelId": "cmni9yocp005vv1nao88h8ygw",
      "sourceId": "cmni9yo7z0000v1naemtfmt98",
      "externalId": "landwatch-455688",
      "url": "https://www.landwatch.com/listing/landwatch-455688",
      "title": "Rolling 264-Acre Estate Tract in Blount County",
      "price": 1700625,
      "pricePerAcre": 6442,
      "status": "listed",
      "photos": "[\"https://images.landscout.dev/landwatch-455688/aerial-1.jpg\",\"https://images.landscout.dev/landwatch-455688/ground-1.jpg\"]",
      "metadata": "{\"originalListDate\":\"2025-09-17\",\"daysOnMarket\":26,\"broker\":null}",
      "firstSeen": "2026-04-03T02:18:49.458Z",
      "lastSeen": "2026-04-03T02:18:49.458Z",
      "createdAt": "2026-04-03T02:18:49.458Z",
      "updatedAt": "2026-04-03T02:18:49.458Z",
      "sourceName": "LandWatch"
    },
    {
      "id": "cmni9yodu00c1v1na53cux5v2",
      "parcelId": "cmni9yocp005vv1nao88h8ygw",
      "sourceId": "cmni9yo7z0005v1na97s98i4z",
      "externalId": "landleader-234748",
      "url": "https://www.landleader.com/listing/landleader-234748",
      "title": "Stunning 264-Acre Mountain Retreat in Blount County",
      "price": 1651568,
      "pricePerAcre": 6256,
      "status": "off-market",
      "photos": "[\"https://images.landscout.dev/landleader-234748/aerial-1.jpg\",\"https://images.landscout.dev/landleader-234748/ground-1.jpg\"]",
      "metadata": "{\"originalListDate\":\"2025-03-11\",\"daysOnMarket\":52,\"broker\":null}",
      "firstSeen": "2026-04-03T02:18:49.458Z",
      "lastSeen": "2026-04-03T02:18:49.458Z",
      "createdAt": "2026-04-03T02:18:49.458Z",
      "updatedAt": "2026-04-03T02:18:49.458Z",
      "sourceName": "LandLeader"
    }
  ],
  "features": {
    "id": "cmni9yocp005wv1na5iyqw02p",
    "parcelId": "cmni9yocp005vv1nao88h8ygw",
    "landCoverMix": "{\"forest\":55,\"wetland\":45}",
    "waterPresence": true,
    "waterFeatures": "[\"pond\"]",
    "metroDistance": 48,
    "nearestMetro": "Birmingham",
    "slopeStats": "{\"mean\":3.9,\"percentOver20\":13,\"percentOver40\":3.2}",
    "soilsQuality": 6.1,
    "roadAccess": "paved",
    "easements": null,
    "powerDistance": 0.6,
    "waterDistance": 3.6,
    "sewerDistance": 16.2,
    "fiberDistance": 29.8,
    "gasDistance": 10,
    "inFloodway": false,
    "floodZone": null,
    "wetlandsPercent": 39.4,
    "elevation": 1744,
    "createdAt": "2026-04-03T02:18:49.417Z",
    "updatedAt": "2026-04-03T02:18:49.417Z"
  },
  "fitScore": {
    "id": "cmni9yocp005xv1nauhugly98",
    "parcelId": "cmni9yocp005vv1nao88h8ygw",
    "overallScore": 61,
    "scoreBreakdown": "{\"acreage\":14,\"soils\":9,\"location\":10,\"access\":14,\"water\":7,\"terrain\":8,\"utilities\":8,\"risk\":4,\"elevation\":3}",
    "topReasons": "[\"Ideal acreage (264 ac) in target range\",\"Paved road access\",\"Water features present on property\",\"Utilities readily available\"]",
    "autoFailed": false,
    "autoFailReason": null,
    "calculatedAt": "2026-04-03T02:18:49.417Z"
  },
  "deal": null,
  "ownership": null
}