{
  "id": "cmni9ugm00034v17iqlaghe9v",
  "apn": null,
  "address": "5380 Cedar Creek Rd",
  "county": "Newberry",
  "state": "SC",
  "acreage": 475,
  "lat": 34.295,
  "lon": -81.5928,
  "zoning": "mixed-use",
  "description": "475-acre mixed-use tract in Newberry County, SC. 46% forest, 30% wetland, 24% pasture. 59 miles from Columbia. Dirt road access. Elevation 751 ft.",
  "createdAt": "2026-04-03T02:15:32.760Z",
  "updatedAt": "2026-04-03T02:15:32.760Z",
  "listings": [
    {
      "id": "cmni9ugn8009fv17ifp4c4saj",
      "parcelId": "cmni9ugm00034v17iqlaghe9v",
      "sourceId": "cmni9ugjf0006v17ijqnwe4qb",
      "externalId": "landwatch-734008",
      "url": "https://www.landwatch.com/listing/landwatch-734008",
      "title": "Exceptional 475-Acre Versatile Tract in Newberry County",
      "price": 6548825,
      "pricePerAcre": 13787,
      "status": "listed",
      "photos": "[\"https://images.landscout.dev/landwatch-734008/aerial-1.jpg\",\"https://images.landscout.dev/landwatch-734008/ground-1.jpg\"]",
      "metadata": "{\"originalListDate\":\"2025-10-17\",\"daysOnMarket\":46,\"broker\":null}",
      "firstSeen": "2026-04-03T02:15:32.804Z",
      "lastSeen": "2026-04-03T02:15:32.804Z",
      "createdAt": "2026-04-03T02:15:32.804Z",
      "updatedAt": "2026-04-03T02:15:32.804Z",
      "sourceName": "LandWatch"
    }
  ],
  "features": {
    "id": "cmni9ugm00035v17iv6thpj1z",
    "parcelId": "cmni9ugm00034v17iqlaghe9v",
    "landCoverMix": "{\"forest\":100}",
    "waterPresence": true,
    "waterFeatures": "[\"water feature\"]",
    "metroDistance": 59.7,
    "nearestMetro": "Greenville, SC",
    "slopeStats": "{\"avgSlope\":1.7,\"maxSlope\":null,\"pctOver15\":0}",
    "soilsQuality": 7,
    "roadAccess": "dirt",
    "easements": null,
    "powerDistance": 2.9,
    "waterDistance": 0.04,
    "sewerDistance": 16,
    "fiberDistance": 12.6,
    "gasDistance": 21,
    "inFloodway": false,
    "floodZone": "X",
    "wetlandsPercent": 26.8,
    "elevation": 518,
    "createdAt": "2026-04-03T02:15:32.760Z",
    "updatedAt": "2026-04-03T02:17:03.640Z"
  },
  "fitScore": {
    "id": "cmni9ugm00036v17i8hmm3v3d",
    "parcelId": "cmni9ugm00034v17iqlaghe9v",
    "overallScore": 63,
    "scoreBreakdown": "{\"acreage\":100,\"landCoverMix\":20,\"waterPresence\":100,\"metroProximity\":14,\"slope\":100,\"soils\":70,\"roadAccess\":45,\"easementPenalty\":100,\"utilities\":20}",
    "topReasons": "[\"+ Ideal acreage for target range (100)\",\"+ Water features present (100)\",\"+ Favorable terrain (100)\",\"- Far from metro areas (14)\",\"- Utilities distant or unavailable (20)\"]",
    "autoFailed": false,
    "autoFailReason": null,
    "calculatedAt": "2026-04-03T02:17:03.643Z"
  },
  "deal": null,
  "ownership": null
}