{
  "totalParcels": 75,
  "totalListings": 106,
  "totalDeals": 25,
  "avgFitScore": 62,
  "highFitCount": 13,
  "medFitCount": 44,
  "lowFitCount": 18,
  "byState": {
    "NC": 14,
    "GA": 13,
    "VA": 13,
    "AL": 12,
    "SC": 12,
    "FL": 11
  },
  "bySources": [
    {
      "sourceId": "cmni3ytoe0000v119fdiqxmfw",
      "count": 14
    },
    {
      "sourceId": "cmni3ytof000bv119dxe27fdp",
      "count": 13
    },
    {
      "sourceId": "cmni3ytoe0003v119zffw1wb2",
      "count": 11
    },
    {
      "sourceId": "cmni3ytof0004v119b1ngv1y5",
      "count": 10
    },
    {
      "sourceId": "cmni3ytoe0002v119p5agsr8r",
      "count": 9
    },
    {
      "sourceId": "cmni3ytof0008v119xun5n3yi",
      "count": 8
    },
    {
      "sourceId": "cmni3ytof0005v119hyjuhysp",
      "count": 7
    },
    {
      "sourceId": "cmni3ytof0006v1193fzr0ces",
      "count": 7
    },
    {
      "sourceId": "cmni3ytof000cv119058d3iys",
      "count": 7
    },
    {
      "sourceId": "cmni3ytof0009v1199kg4bvri",
      "count": 6
    },
    {
      "sourceId": "cmni3ytoe0001v119n6x5u41m",
      "count": 5
    },
    {
      "sourceId": "cmni3ytof000av119r909sr29",
      "count": 5
    },
    {
      "sourceId": "cmni3ytof0007v119sfdrqtbu",
      "count": 4
    }
  ]
}